kolla/__init__.py
kolla/exception.py
kolla/opts.py
kolla/version.py
kolla/cmd/__init__.py
kolla/cmd/build.py
kolla/common/__init__.py
kolla/common/config.py
kolla/common/sources.py
kolla/common/task.py
kolla/common/users.py
kolla/common/utils.py
kolla/engine_adapter/__init__.py
kolla/engine_adapter/engine.py
kolla/hacking/__init__.py
kolla/hacking/checks.py
kolla/image/__init__.py
kolla/image/build.py
kolla/image/kolla_worker.py
kolla/image/tasks.py
kolla/image/unbuildable.py
kolla/image/utils.py
kolla/template/__init__.py
kolla/template/filters.py
kolla/template/methods.py
kolla/template/repos.yaml
kolla/tests/__init__.py
kolla/tests/base.py
kolla/tests/test_build.py
kolla/tests/test_hacking.py
kolla/tests/test_methods.py
kolla/tests/common/__init__.py
kolla/tests/common/test_config.py
kolla/tests/docker/base/Dockerfile.j2
kolla/tests/docker/etcd/Dockerfile.j2
kolla/tests/docker/neutron-server/Dockerfile.j2
kolla/tests/etc/default.conf
kolla-21.0.0.data/data/share/kolla/setup.cfg
kolla-21.0.0.data/data/share/kolla/contrib/neutron-plugins/README.rst
kolla-21.0.0.data/data/share/kolla/contrib/neutron-plugins/networking-ansible.ini
kolla-21.0.0.data/data/share/kolla/contrib/neutron-plugins/networking-mlnx.ini
kolla-21.0.0.data/data/share/kolla/contrib/neutron-plugins/template_override-networking-mlnx.j2
kolla-21.0.0.data/data/share/kolla/contrib/neutron-plugins/template_override-vmware-nsx.j2
kolla-21.0.0.data/data/share/kolla/contrib/neutron-plugins/vmware-nsx.ini
kolla-21.0.0.data/data/share/kolla/contrib/template-override/README.rst
kolla-21.0.0.data/data/share/kolla/contrib/template-override/ovs-dpdk.j2
kolla-21.0.0.data/data/share/kolla/doc/requirements.txt
kolla-21.0.0.data/data/share/kolla/doc/source/ceph_versions.csv
kolla-21.0.0.data/data/share/kolla/doc/source/conf.py
kolla-21.0.0.data/data/share/kolla/doc/source/index.rst
kolla-21.0.0.data/data/share/kolla/doc/source/matrix_aarch64.csv
kolla-21.0.0.data/data/share/kolla/doc/source/matrix_x86.csv
kolla-21.0.0.dist-info/AUTHORS
kolla-21.0.0.dist-info/LICENSE
kolla-21.0.0.dist-info/METADATA
kolla-21.0.0.dist-info/WHEEL
kolla-21.0.0.dist-info/entry_points.txt
kolla-21.0.0.dist-info/pbr.json
kolla-21.0.0.dist-info/top_level.txt
kolla-21.0.0.dist-info/RECORD
